shacltool/__init__.py
shacltool/owl2shacl.py
telicent_owl2shacl-0.2.4.dist-info/LICENSE.md
telicent_owl2shacl-0.2.4.dist-info/METADATA
telicent_owl2shacl-0.2.4.dist-info/WHEEL
telicent_owl2shacl-0.2.4.dist-info/entry_points.txt
telicent_owl2shacl-0.2.4.dist-info/top_level.txt
telicent_owl2shacl-0.2.4.dist-info/RECORD
