Metadata-Version: 2.1
Name: telicent-owl2shacl
Version: 0.2.4
Summary: Tool for generating shacl and validating instance data against that shacl and ontology.
Author-email: Telicent Ltd <opensource@telicent.io>
License: © Crown copyright (2023). 
Project-URL: Repository, https://github.com/Telicent-io/shacl-tool
Classifier: Programming Language :: Python :: 3.11
Classifier: Programming Language :: Python :: 3.12
Classifier: Programming Language :: Python :: 3 :: Only
Classifier: Topic :: Software Development
Classifier: Operating System :: Microsoft :: Windows
Classifier: Operating System :: POSIX
Classifier: Operating System :: Unix
Classifier: Operating System :: MacOS
Requires-Python: >=3.11
License-File: LICENSE.md
Requires-Dist: argcomplete >=3.1.1
Requires-Dist: cffi >=1.15.1
Requires-Dist: click >=8.1.6
Requires-Dist: docutils >=0.20.1
Requires-Dist: html5lib >=1.1
Requires-Dist: isodate >=0.6.1
Requires-Dist: owlrl >=6.0.2
Requires-Dist: packaging >=23.1
Requires-Dist: pipx >=1.2.0
Requires-Dist: prettytable >=2.5.0
Requires-Dist: pycparser >=2.21
Requires-Dist: pyparsing >=3.1.0
Requires-Dist: pyshacl >=0.23.0
Requires-Dist: rdflib >=6.3.2
Requires-Dist: six >=1.16.0
Requires-Dist: typing >=3.7.4.3
Requires-Dist: userpath >=1.9.0
Requires-Dist: wcwidth >=0.2.6
Requires-Dist: webencodings >=0.5.1
Provides-Extra: dev
Requires-Dist: pre-commit ==3.5.0 ; extra == 'dev'
Requires-Dist: ruff ==0.1.5 ; extra == 'dev'
Requires-Dist: types-pytz ==2023.3.1.1 ; extra == 'dev'
Requires-Dist: types-requests ==2.31.0.10 ; extra == 'dev'
Requires-Dist: mypy ==1.7.0 ; extra == 'dev'
Requires-Dist: pytest ==8.2.1 ; extra == 'dev'
Requires-Dist: cyclonedx-bom ==4.4.3 ; extra == 'dev'
